nonebot_plugin_random_cat/__init__.py
nonebot_plugin_random_cat/config.py
nonebot_plugin_random_cat/get_data.py
nonebot_plugin_random_cat-0.1.0.dist-info/LICENSE
nonebot_plugin_random_cat-0.1.0.dist-info/WHEEL
nonebot_plugin_random_cat-0.1.0.dist-info/METADATA
nonebot_plugin_random_cat-0.1.0.dist-info/RECORD
