Metadata-Version: 2.1
Name: nonebot-plugin-random-cat
Version: 0.1.0
Summary: 
License: MIT
Author: alphaAE
Author-email: a1226123914@gmail.com
Requires-Python: >=3.9,<4.0
Classifier: License :: OSI Approved :: MIT License
Classifier: Programming Language :: Python :: 3
Classifier: Programming Language :: Python :: 3.10
Classifier: Programming Language :: Python :: 3.9
Requires-Dist: httpx (>=0.22.0,<0.23.0)
Requires-Dist: httpx-socks (>=0.7.3,<0.8.0)
